README.md
setup.py
roblopy/__init__.py
roblopy/assets.py
roblopy/friends.py
roblopy/groups.py
roblopy/user.py
roblopy.egg-info/PKG-INFO
roblopy.egg-info/SOURCES.txt
roblopy.egg-info/dependency_links.txt
roblopy.egg-info/requires.txt
roblopy.egg-info/top_level.txt
roblopy/utils/errors.py
roblopy/utils/request.py