Metadata-Version: 2.1
Name: roblopy
Version: 5.0
Summary: Roblox API built in Python
Home-page: https://github.com/jackprogramsjp/Roblopy
Author: Jack Murrow
Author-email: jack.murrow122005@gmail.com
License: MIT
Keywords: Roblox,Roblox Python,Roblox Api
Platform: UNKNOWN
Classifier: Programming Language :: Python :: 3
Classifier: License :: OSI Approved :: MIT License
